[
  {
    "Wk": 1,
    "Date": "2024-08-16",
    "Time": "20:00",
    "Home": "Manchester Utd",
    "HomeCode": "MUN",
    "Score": "1-0",
    "Away": "Fulham",
    "AwayCode": "FUL"
  },
  {
    "Wk": 1,
    "Date": "2024-08-17",
    "Time": "12:30",
    "Home": "Ipswich Town",
    "HomeCode": "IPS",
    "Score": "0-2",
    "Away": "Liverpool",
    "AwayCode": "LIV"
  },
  {
    "Wk": 1,
    "Date": "2024-08-17",
    "Time": "15:00",
    "Home": "Newcastle Utd",
    "HomeCode": "NEW",
    "Score": "1-0",
    "Away": "Southampton",
    "AwayCode": "SOU"
  },
  {
    "Wk": 1,
    "Date": "2024-08-17",
    "Time": "15:00",
    "Home": "Nott'ham Forest",
    "HomeCode": "NFO",
    "Score": "1-1",
    "Away": "Bournemouth",
    "AwayCode": "BOU"
  },
  {
    "Wk": 1,
    "Date": "2024-08-17",
    "Time": "15:00",
    "Home": "Everton",
    "HomeCode": "EVE",
    "Score": "0-3",
    "Away": "Brighton",
    "AwayCode": "BHA"
  },
  {
    "Wk": 1,
    "Date": "2024-08-17",
    "Time": "15:00",
    "Home": "Arsenal",
    "HomeCode": "ARS",
    "Score": "2-0",
    "Away": "Wolves",
    "AwayCode": "WOL"
  },
  {
    "Wk": 1,
    "Date": "2024-08-17",
    "Time": "17:30",
    "Home": "West Ham",
    "HomeCode": "WHU",
    "Score": "1-2",
    "Away": "Aston Villa",
    "AwayCode": "AVL"
  },
  {
    "Wk": 1,
    "Date": "2024-08-18",
    "Time": "14:00",
    "Home": "Brentford",
    "HomeCode": "BRE",
    "Score": "2-1",
    "Away": "Crystal Palace",
    "AwayCode": "CRY"
  },
  {
    "Wk": 1,
    "Date": "2024-08-18",
    "Time": "16:30",
    "Home": "Chelsea",
    "HomeCode": "CHE",
    "Score": "0-2",
    "Away": "Manchester City",
    "AwayCode": "MCI"
  },
  {
    "Wk": 1,
    "Date": "2024-08-19",
    "Time": "20:00",
    "Home": "Leicester City",
    "HomeCode": "LEI",
    "Score": "1-1",
    "Away": "Tottenham",
    "AwayCode": "TOT"
  },
  {
    "Wk": 2,
    "Date": "2024-08-24",
    "Time": "12:30",
    "Home": "Brighton",
    "HomeCode": "BHA",
    "Score": "2-1",
    "Away": "Manchester Utd",
    "AwayCode": "MUN"
  },
  {
    "Wk": 2,
    "Date": "2024-08-24",
    "Time": "15:00",
    "Home": "Tottenham",
    "HomeCode": "TOT",
    "Score": "4-0",
    "Away": "Everton",
    "AwayCode": "EVE"
  },
  {
    "Wk": 2,
    "Date": "2024-08-24",
    "Time": "15:00",
    "Home": "Fulham",
    "HomeCode": "FUL",
    "Score": "2-1",
    "Away": "Leicester City",
    "AwayCode": "LEI"
  },
  {
    "Wk": 2,
    "Date": "2024-08-24",
    "Time": "15:00",
    "Home": "Crystal Palace",
    "HomeCode": "CRY",
    "Score": "0-2",
    "Away": "West Ham",
    "AwayCode": "WHU"
  },
  {
    "Wk": 2,
    "Date": "2024-08-24",
    "Time": "15:00",
    "Home": "Manchester City",
    "HomeCode": "MCI",
    "Score": "4-1",
    "Away": "Ipswich Town",
    "AwayCode": "IPS"
  },
  {
    "Wk": 2,
    "Date": "2024-08-24",
    "Time": "15:00",
    "Home": "Southampton",
    "HomeCode": "SOU",
    "Score": "0-1",
    "Away": "Nott'ham Forest",
    "AwayCode": "NFO"
  },
  {
    "Wk": 2,
    "Date": "2024-08-24",
    "Time": "17:30",
    "Home": "Aston Villa",
    "HomeCode": "AVL",
    "Score": "0-2",
    "Away": "Arsenal",
    "AwayCode": "ARS"
  },
  {
    "Wk": 2,
    "Date": "2024-08-25",
    "Time": "14:00",
    "Home": "Bournemouth",
    "HomeCode": "BOU",
    "Score": "1-1",
    "Away": "Newcastle Utd",
    "AwayCode": "NEW"
  },
  {
    "Wk": 2,
    "Date": "2024-08-25",
    "Time": "14:00",
    "Home": "Wolves",
    "HomeCode": "WOL",
    "Score": "2-6",
    "Away": "Chelsea",
    "AwayCode": "CHE"
  },
  {
    "Wk": 2,
    "Date": "2024-08-25",
    "Time": "16:30",
    "Home": "Liverpool",
    "HomeCode": "LIV",
    "Score": "2-0",
    "Away": "Brentford",
    "AwayCode": "BRE"
  },
  {
    "Wk": 3,
    "Date": "2024-08-31",
    "Time": "12:30",
    "Home": "Arsenal",
    "HomeCode": "ARS",
    "Score": "1-1",
    "Away": "Brighton",
    "AwayCode": "BHA"
  },
  {
    "Wk": 3,
    "Date": "2024-08-31",
    "Time": "15:00",
    "Home": "Everton",
    "HomeCode": "EVE",
    "Score": "2-3",
    "Away": "Bournemouth",
    "AwayCode": "BOU"
  },
  {
    "Wk": 3,
    "Date": "2024-08-31",
    "Time": "15:00",
    "Home": "Leicester City",
    "HomeCode": "LEI",
    "Score": "1-2",
    "Away": "Aston Villa",
    "AwayCode": "AVL"
  },
  {
    "Wk": 3,
    "Date": "2024-08-31",
    "Time": "15:00",
    "Home": "Nott'ham Forest",
    "HomeCode": "NFO",
    "Score": "1-1",
    "Away": "Wolves",
    "AwayCode": "WOL"
  },
  {
    "Wk": 3,
    "Date": "2024-08-31",
    "Time": "15:00",
    "Home": "Ipswich Town",
    "HomeCode": "IPS",
    "Score": "1-1",
    "Away": "Fulham",
    "AwayCode": "FUL"
  },
  {
    "Wk": 3,
    "Date": "2024-08-31",
    "Time": "15:00",
    "Home": "Brentford",
    "HomeCode": "BRE",
    "Score": "3-1",
    "Away": "Southampton",
    "AwayCode": "SOU"
  },
  {
    "Wk": 3,
    "Date": "2024-08-31",
    "Time": "17:30",
    "Home": "West Ham",
    "HomeCode": "WHU",
    "Score": "1-3",
    "Away": "Manchester City",
    "AwayCode": "MCI"
  },
  {
    "Wk": 3,
    "Date": "2024-09-01",
    "Time": "13:30",
    "Home": "Newcastle Utd",
    "HomeCode": "NEW",
    "Score": "2-1",
    "Away": "Tottenham",
    "AwayCode": "TOT"
  },
  {
    "Wk": 3,
    "Date": "2024-09-01",
    "Time": "13:30",
    "Home": "Chelsea",
    "HomeCode": "CHE",
    "Score": "1-1",
    "Away": "Crystal Palace",
    "AwayCode": "CRY"
  },
  {
    "Wk": 3,
    "Date": "2024-09-01",
    "Time": "16:00",
    "Home": "Manchester Utd",
    "HomeCode": "MUN",
    "Score": "0-3",
    "Away": "Liverpool",
    "AwayCode": "LIV"
  },
  {
    "Wk": 4,
    "Date": "2024-09-14",
    "Time": "12:30",
    "Home": "Southampton",
    "HomeCode": "SOU",
    "Score": "0-3",
    "Away": "Manchester Utd",
    "AwayCode": "MUN"
  },
  {
    "Wk": 4,
    "Date": "2024-09-14",
    "Time": "15:00",
    "Home": "Brighton",
    "HomeCode": "BHA",
    "Score": "0-0",
    "Away": "Ipswich Town",
    "AwayCode": "IPS"
  },
  {
    "Wk": 4,
    "Date": "2024-09-14",
    "Time": "15:00",
    "Home": "Crystal Palace",
    "HomeCode": "CRY",
    "Score": "2-2",
    "Away": "Leicester City",
    "AwayCode": "LEI"
  },
  {
    "Wk": 4,
    "Date": "2024-09-14",
    "Time": "15:00",
    "Home": "Manchester City",
    "HomeCode": "MCI",
    "Score": "2-1",
    "Away": "Brentford",
    "AwayCode": "BRE"
  },
  {
    "Wk": 4,
    "Date": "2024-09-14",
    "Time": "15:00",
    "Home": "Liverpool",
    "HomeCode": "LIV",
    "Score": "0-1",
    "Away": "Nott'ham Forest",
    "AwayCode": "NFO"
  },
  {
    "Wk": 4,
    "Date": "2024-09-14",
    "Time": "15:00",
    "Home": "Fulham",
    "HomeCode": "FUL",
    "Score": "1-1",
    "Away": "West Ham",
    "AwayCode": "WHU"
  },
  {
    "Wk": 4,
    "Date": "2024-09-14",
    "Time": "17:30",
    "Home": "Aston Villa",
    "HomeCode": "AVL",
    "Score": "3-2",
    "Away": "Everton",
    "AwayCode": "EVE"
  },
  {
    "Wk": 4,
    "Date": "2024-09-14",
    "Time": "20:00",
    "Home": "Bournemouth",
    "HomeCode": "BOU",
    "Score": "0-1",
    "Away": "Chelsea",
    "AwayCode": "CHE"
  },
  {
    "Wk": 4,
    "Date": "2024-09-15",
    "Time": "14:00",
    "Home": "Tottenham",
    "HomeCode": "TOT",
    "Score": "0-1",
    "Away": "Arsenal",
    "AwayCode": "ARS"
  },
  {
    "Wk": 4,
    "Date": "2024-09-15",
    "Time": "16:30",
    "Home": "Wolves",
    "HomeCode": "WOL",
    "Score": "1-2",
    "Away": "Newcastle Utd",
    "AwayCode": "NEW"
  },
  {
    "Wk": 5,
    "Date": "2024-09-21",
    "Time": "12:30",
    "Home": "West Ham",
    "HomeCode": "WHU",
    "Score": "0-3",
    "Away": "Chelsea",
    "AwayCode": "CHE"
  },
  {
    "Wk": 5,
    "Date": "2024-09-21",
    "Time": "15:00",
    "Home": "Liverpool",
    "HomeCode": "LIV",
    "Score": "3-0",
    "Away": "Bournemouth",
    "AwayCode": "BOU"
  },
  {
    "Wk": 5,
    "Date": "2024-09-21",
    "Time": "15:00",
    "Home": "Leicester City",
    "HomeCode": "LEI",
    "Score": "1-1",
    "Away": "Everton",
    "AwayCode": "EVE"
  },
  {
    "Wk": 5,
    "Date": "2024-09-21",
    "Time": "15:00",
    "Home": "Southampton",
    "HomeCode": "SOU",
    "Score": "1-1",
    "Away": "Ipswich Town",
    "AwayCode": "IPS"
  },
  {
    "Wk": 5,
    "Date": "2024-09-21",
    "Time": "15:00",
    "Home": "Tottenham",
    "HomeCode": "TOT",
    "Score": "3-1",
    "Away": "Brentford",
    "AwayCode": "BRE"
  },
  {
    "Wk": 5,
    "Date": "2024-09-21",
    "Time": "15:00",
    "Home": "Fulham",
    "HomeCode": "FUL",
    "Score": "3-1",
    "Away": "Newcastle Utd",
    "AwayCode": "NEW"
  },
  {
    "Wk": 5,
    "Date": "2024-09-21",
    "Time": "15:00",
    "Home": "Aston Villa",
    "HomeCode": "AVL",
    "Score": "3-1",
    "Away": "Wolves",
    "AwayCode": "WOL"
  },
  {
    "Wk": 5,
    "Date": "2024-09-21",
    "Time": "17:30",
    "Home": "Crystal Palace",
    "HomeCode": "CRY",
    "Score": "0-0",
    "Away": "Manchester Utd",
    "AwayCode": "MUN"
  },
  {
    "Wk": 5,
    "Date": "2024-09-22",
    "Time": "14:00",
    "Home": "Brighton",
    "HomeCode": "BHA",
    "Score": "2-2",
    "Away": "Nott'ham Forest",
    "AwayCode": "NFO"
  },
  {
    "Wk": 5,
    "Date": "2024-09-22",
    "Time": "16:30",
    "Home": "Manchester City",
    "HomeCode": "MCI",
    "Score": "2-2",
    "Away": "Arsenal",
    "AwayCode": "ARS"
  },
  {
    "Wk": 6,
    "Date": "2024-09-28",
    "Time": "12:30",
    "Home": "Newcastle Utd",
    "HomeCode": "NEW",
    "Score": "1-1",
    "Away": "Manchester City",
    "AwayCode": "MCI"
  },
  {
    "Wk": 6,
    "Date": "2024-09-28",
    "Time": "15:00",
    "Home": "Chelsea",
    "HomeCode": "CHE",
    "Score": "4-2",
    "Away": "Brighton",
    "AwayCode": "BHA"
  },
  {
    "Wk": 6,
    "Date": "2024-09-28",
    "Time": "15:00",
    "Home": "Arsenal",
    "HomeCode": "ARS",
    "Score": "4-2",
    "Away": "Leicester City",
    "AwayCode": "LEI"
  },
  {
    "Wk": 6,
    "Date": "2024-09-28",
    "Time": "15:00",
    "Home": "Brentford",
    "HomeCode": "BRE",
    "Score": "1-1",
    "Away": "West Ham",
    "AwayCode": "WHU"
  },
  {
    "Wk": 6,
    "Date": "2024-09-28",
    "Time": "15:00",
    "Home": "Everton",
    "HomeCode": "EVE",
    "Score": "2-1",
    "Away": "Crystal Palace",
    "AwayCode": "CRY"
  },
  {
    "Wk": 6,
    "Date": "2024-09-28",
    "Time": "15:00",
    "Home": "Nott'ham Forest",
    "HomeCode": "NFO",
    "Score": "0-1",
    "Away": "Fulham",
    "AwayCode": "FUL"
  },
  {
    "Wk": 6,
    "Date": "2024-09-28",
    "Time": "17:30",
    "Home": "Wolves",
    "HomeCode": "WOL",
    "Score": "1-2",
    "Away": "Liverpool",
    "AwayCode": "LIV"
  },
  {
    "Wk": 6,
    "Date": "2024-09-29",
    "Time": "14:00",
    "Home": "Ipswich Town",
    "HomeCode": "IPS",
    "Score": "2-2",
    "Away": "Aston Villa",
    "AwayCode": "AVL"
  },
  {
    "Wk": 6,
    "Date": "2024-09-29",
    "Time": "16:30",
    "Home": "Manchester Utd",
    "HomeCode": "MUN",
    "Score": "0-3",
    "Away": "Tottenham",
    "AwayCode": "TOT"
  },
  {
    "Wk": 6,
    "Date": "2024-09-30",
    "Time": "20:00",
    "Home": "Bournemouth",
    "HomeCode": "BOU",
    "Score": "3-1",
    "Away": "Southampton",
    "AwayCode": "SOU"
  },
  {
    "Wk": 7,
    "Date": "2024-10-05",
    "Time": "12:30",
    "Home": "Crystal Palace",
    "HomeCode": "CRY",
    "Score": "0-1",
    "Away": "Liverpool",
    "AwayCode": "LIV"
  },
  {
    "Wk": 7,
    "Date": "2024-10-05",
    "Time": "15:00",
    "Home": "Manchester City",
    "HomeCode": "MCI",
    "Score": "3-2",
    "Away": "Fulham",
    "AwayCode": "FUL"
  },
  {
    "Wk": 7,
    "Date": "2024-10-05",
    "Time": "15:00",
    "Home": "Brentford",
    "HomeCode": "BRE",
    "Score": "5-3",
    "Away": "Wolves",
    "AwayCode": "WOL"
  },
  {
    "Wk": 7,
    "Date": "2024-10-05",
    "Time": "15:00",
    "Home": "West Ham",
    "HomeCode": "WHU",
    "Score": "4-1",
    "Away": "Ipswich Town",
    "AwayCode": "IPS"
  },
  {
    "Wk": 7,
    "Date": "2024-10-05",
    "Time": "15:00",
    "Home": "Arsenal",
    "HomeCode": "ARS",
    "Score": "3-1",
    "Away": "Southampton",
    "AwayCode": "SOU"
  },
  {
    "Wk": 7,
    "Date": "2024-10-05",
    "Time": "15:00",
    "Home": "Leicester City",
    "HomeCode": "LEI",
    "Score": "1-0",
    "Away": "Bournemouth",
    "AwayCode": "BOU"
  },
  {
    "Wk": 7,
    "Date": "2024-10-05",
    "Time": "17:30",
    "Home": "Everton",
    "HomeCode": "EVE",
    "Score": "0-0",
    "Away": "Newcastle Utd",
    "AwayCode": "NEW"
  },
  {
    "Wk": 7,
    "Date": "2024-10-06",
    "Time": "14:00",
    "Home": "Aston Villa",
    "HomeCode": "AVL",
    "Score": "0-0",
    "Away": "Manchester Utd",
    "AwayCode": "MUN"
  },
  {
    "Wk": 7,
    "Date": "2024-10-06",
    "Time": "14:00",
    "Home": "Chelsea",
    "HomeCode": "CHE",
    "Score": "1-1",
    "Away": "Nott'ham Forest",
    "AwayCode": "NFO"
  },
  {
    "Wk": 7,
    "Date": "2024-10-06",
    "Time": "16:30",
    "Home": "Brighton",
    "HomeCode": "BHA",
    "Score": "3-2",
    "Away": "Tottenham",
    "AwayCode": "TOT"
  },
  {
    "Wk": 8,
    "Date": "2024-10-19",
    "Time": "12:30",
    "Home": "Tottenham",
    "HomeCode": "TOT",
    "Score": "4-1",
    "Away": "West Ham",
    "AwayCode": "WHU"
  },
  {
    "Wk": 8,
    "Date": "2024-10-19",
    "Time": "15:00",
    "Home": "Southampton",
    "HomeCode": "SOU",
    "Score": "2-3",
    "Away": "Leicester City",
    "AwayCode": "LEI"
  },
  {
    "Wk": 8,
    "Date": "2024-10-19",
    "Time": "15:00",
    "Home": "Ipswich Town",
    "HomeCode": "IPS",
    "Score": "0-2",
    "Away": "Everton",
    "AwayCode": "EVE"
  },
  {
    "Wk": 8,
    "Date": "2024-10-19",
    "Time": "15:00",
    "Home": "Newcastle Utd",
    "HomeCode": "NEW",
    "Score": "0-1",
    "Away": "Brighton",
    "AwayCode": "BHA"
  },
  {
    "Wk": 8,
    "Date": "2024-10-19",
    "Time": "15:00",
    "Home": "Fulham",
    "HomeCode": "FUL",
    "Score": "1-3",
    "Away": "Aston Villa",
    "AwayCode": "AVL"
  },
  {
    "Wk": 8,
    "Date": "2024-10-19",
    "Time": "15:00",
    "Home": "Manchester Utd",
    "HomeCode": "MUN",
    "Score": "2-1",
    "Away": "Brentford",
    "AwayCode": "BRE"
  },
  {
    "Wk": 8,
    "Date": "2024-10-19",
    "Time": "17:30",
    "Home": "Bournemouth",
    "HomeCode": "BOU",
    "Score": "2-0",
    "Away": "Arsenal",
    "AwayCode": "ARS"
  },
  {
    "Wk": 8,
    "Date": "2024-10-20",
    "Time": "14:00",
    "Home": "Wolves",
    "HomeCode": "WOL",
    "Score": "1-2",
    "Away": "Manchester City",
    "AwayCode": "MCI"
  },
  {
    "Wk": 8,
    "Date": "2024-10-20",
    "Time": "16:30",
    "Home": "Liverpool",
    "HomeCode": "LIV",
    "Score": "2-1",
    "Away": "Chelsea",
    "AwayCode": "CHE"
  },
  {
    "Wk": 8,
    "Date": "2024-10-21",
    "Time": "20:00",
    "Home": "Nott'ham Forest",
    "HomeCode": "NFO",
    "Score": "1-0",
    "Away": "Crystal Palace",
    "AwayCode": "CRY"
  },
  {
    "Wk": 9,
    "Date": "2024-10-25",
    "Time": "20:00",
    "Home": "Leicester City",
    "HomeCode": "LEI",
    "Score": "1-3",
    "Away": "Nott'ham Forest",
    "AwayCode": "NFO"
  },
  {
    "Wk": 9,
    "Date": "2024-10-26",
    "Time": "15:00",
    "Home": "Brentford",
    "HomeCode": "BRE",
    "Score": "4-3",
    "Away": "Ipswich Town",
    "AwayCode": "IPS"
  },
  {
    "Wk": 9,
    "Date": "2024-10-26",
    "Time": "15:00",
    "Home": "Brighton",
    "HomeCode": "BHA",
    "Score": "2-2",
    "Away": "Wolves",
    "AwayCode": "WOL"
  },
  {
    "Wk": 9,
    "Date": "2024-10-26",
    "Time": "15:00",
    "Home": "Manchester City",
    "HomeCode": "MCI",
    "Score": "1-0",
    "Away": "Southampton",
    "AwayCode": "SOU"
  },
  {
    "Wk": 9,
    "Date": "2024-10-26",
    "Time": "15:00",
    "Home": "Aston Villa",
    "HomeCode": "AVL",
    "Score": "1-1",
    "Away": "Bournemouth",
    "AwayCode": "BOU"
  },
  {
    "Wk": 9,
    "Date": "2024-10-26",
    "Time": "17:30",
    "Home": "Everton",
    "HomeCode": "EVE",
    "Score": "1-1",
    "Away": "Fulham",
    "AwayCode": "FUL"
  },
  {
    "Wk": 9,
    "Date": "2024-10-27",
    "Time": "14:00",
    "Home": "Chelsea",
    "HomeCode": "CHE",
    "Score": "2-1",
    "Away": "Newcastle Utd",
    "AwayCode": "NEW"
  },
  {
    "Wk": 9,
    "Date": "2024-10-27",
    "Time": "14:00",
    "Home": "West Ham",
    "HomeCode": "WHU",
    "Score": "2-1",
    "Away": "Manchester Utd",
    "AwayCode": "MUN"
  },
  {
    "Wk": 9,
    "Date": "2024-10-27",
    "Time": "14:00",
    "Home": "Crystal Palace",
    "HomeCode": "CRY",
    "Score": "1-0",
    "Away": "Tottenham",
    "AwayCode": "TOT"
  },
  {
    "Wk": 9,
    "Date": "2024-10-27",
    "Time": "16:30",
    "Home": "Arsenal",
    "HomeCode": "ARS",
    "Score": "2-2",
    "Away": "Liverpool",
    "AwayCode": "LIV"
  },
  {
    "Wk": 10,
    "Date": "2024-11-02",
    "Time": "12:30",
    "Home": "Newcastle Utd",
    "HomeCode": "NEW",
    "Score": "1-0",
    "Away": "Arsenal",
    "AwayCode": "ARS"
  },
  {
    "Wk": 10,
    "Date": "2024-11-02",
    "Time": "15:00",
    "Home": "Southampton",
    "HomeCode": "SOU",
    "Score": "1-0",
    "Away": "Everton",
    "AwayCode": "EVE"
  },
  {
    "Wk": 10,
    "Date": "2024-11-02",
    "Time": "15:00",
    "Home": "Liverpool",
    "HomeCode": "LIV",
    "Score": "2-1",
    "Away": "Brighton",
    "AwayCode": "BHA"
  },
  {
    "Wk": 10,
    "Date": "2024-11-02",
    "Time": "15:00",
    "Home": "Nott'ham Forest",
    "HomeCode": "NFO",
    "Score": "3-0",
    "Away": "West Ham",
    "AwayCode": "WHU"
  },
  {
    "Wk": 10,
    "Date": "2024-11-02",
    "Time": "15:00",
    "Home": "Ipswich Town",
    "HomeCode": "IPS",
    "Score": "1-1",
    "Away": "Leicester City",
    "AwayCode": "LEI"
  },
  {
    "Wk": 10,
    "Date": "2024-11-02",
    "Time": "15:00",
    "Home": "Bournemouth",
    "HomeCode": "BOU",
    "Score": "2-1",
    "Away": "Manchester City",
    "AwayCode": "MCI"
  },
  {
    "Wk": 10,
    "Date": "2024-11-02",
    "Time": "17:30",
    "Home": "Wolves",
    "HomeCode": "WOL",
    "Score": "2-2",
    "Away": "Crystal Palace",
    "AwayCode": "CRY"
  },
  {
    "Wk": 10,
    "Date": "2024-11-03",
    "Time": "14:00",
    "Home": "Tottenham",
    "HomeCode": "TOT",
    "Score": "4-1",
    "Away": "Aston Villa",
    "AwayCode": "AVL"
  },
  {
    "Wk": 10,
    "Date": "2024-11-03",
    "Time": "16:30",
    "Home": "Manchester Utd",
    "HomeCode": "MUN",
    "Score": "1-1",
    "Away": "Chelsea",
    "AwayCode": "CHE"
  },
  {
    "Wk": 10,
    "Date": "2024-11-04",
    "Time": "20:00",
    "Home": "Fulham",
    "HomeCode": "FUL",
    "Score": "2-1",
    "Away": "Brentford",
    "AwayCode": "BRE"
  },
  {
    "Wk": 11,
    "Date": "2024-11-09",
    "Time": "15:00",
    "Home": "Brentford",
    "HomeCode": "BRE",
    "Score": "3-2",
    "Away": "Bournemouth",
    "AwayCode": "BOU"
  },
  {
    "Wk": 11,
    "Date": "2024-11-09",
    "Time": "15:00",
    "Home": "West Ham",
    "HomeCode": "WHU",
    "Score": "0-0",
    "Away": "Everton",
    "AwayCode": "EVE"
  },
  {
    "Wk": 11,
    "Date": "2024-11-09",
    "Time": "15:00",
    "Home": "Crystal Palace",
    "HomeCode": "CRY",
    "Score": "0-2",
    "Away": "Fulham",
    "AwayCode": "FUL"
  },
  {
    "Wk": 11,
    "Date": "2024-11-09",
    "Time": "15:00",
    "Home": "Wolves",
    "HomeCode": "WOL",
    "Score": "2-0",
    "Away": "Southampton",
    "AwayCode": "SOU"
  },
  {
    "Wk": 11,
    "Date": "2024-11-09",
    "Time": "17:30",
    "Home": "Brighton",
    "HomeCode": "BHA",
    "Score": "2-1",
    "Away": "Manchester City",
    "AwayCode": "MCI"
  },
  {
    "Wk": 11,
    "Date": "2024-11-09",
    "Time": "20:00",
    "Home": "Liverpool",
    "HomeCode": "LIV",
    "Score": "2-0",
    "Away": "Aston Villa",
    "AwayCode": "AVL"
  },
  {
    "Wk": 11,
    "Date": "2024-11-10",
    "Time": "14:00",
    "Home": "Manchester Utd",
    "HomeCode": "MUN",
    "Score": "3-0",
    "Away": "Leicester City",
    "AwayCode": "LEI"
  },
  {
    "Wk": 11,
    "Date": "2024-11-10",
    "Time": "14:00",
    "Home": "Nott'ham Forest",
    "HomeCode": "NFO",
    "Score": "1-3",
    "Away": "Newcastle Utd",
    "AwayCode": "NEW"
  },
  {
    "Wk": 11,
    "Date": "2024-11-10",
    "Time": "14:00",
    "Home": "Tottenham",
    "HomeCode": "TOT",
    "Score": "1-2",
    "Away": "Ipswich Town",
    "AwayCode": "IPS"
  },
  {
    "Wk": 11,
    "Date": "2024-11-10",
    "Time": "16:30",
    "Home": "Chelsea",
    "HomeCode": "CHE",
    "Score": "1-1",
    "Away": "Arsenal",
    "AwayCode": "ARS"
  },
  {
    "Wk": 12,
    "Date": "2024-11-23",
    "Time": "12:30",
    "Home": "Leicester City",
    "HomeCode": "LEI",
    "Score": "1-2",
    "Away": "Chelsea",
    "AwayCode": "CHE"
  },
  {
    "Wk": 12,
    "Date": "2024-11-23",
    "Time": "15:00",
    "Home": "Arsenal",
    "HomeCode": "ARS",
    "Score": "3-0",
    "Away": "Nott'ham Forest",
    "AwayCode": "NFO"
  },
  {
    "Wk": 12,
    "Date": "2024-11-23",
    "Time": "15:00",
    "Home": "Bournemouth",
    "HomeCode": "BOU",
    "Score": "1-2",
    "Away": "Brighton",
    "AwayCode": "BHA"
  },
  {
    "Wk": 12,
    "Date": "2024-11-23",
    "Time": "15:00",
    "Home": "Aston Villa",
    "HomeCode": "AVL",
    "Score": "2-2",
    "Away": "Crystal Palace",
    "AwayCode": "CRY"
  },
  {
    "Wk": 12,
    "Date": "2024-11-23",
    "Time": "15:00",
    "Home": "Everton",
    "HomeCode": "EVE",
    "Score": "0-0",
    "Away": "Brentford",
    "AwayCode": "BRE"
  },
  {
    "Wk": 12,
    "Date": "2024-11-23",
    "Time": "15:00",
    "Home": "Fulham",
    "HomeCode": "FUL",
    "Score": "1-4",
    "Away": "Wolves",
    "AwayCode": "WOL"
  },
  {
    "Wk": 12,
    "Date": "2024-11-23",
    "Time": "17:30",
    "Home": "Manchester City",
    "HomeCode": "MCI",
    "Score": "0-4",
    "Away": "Tottenham",
    "AwayCode": "TOT"
  },
  {
    "Wk": 12,
    "Date": "2024-11-24",
    "Time": "14:00",
    "Home": "Southampton",
    "HomeCode": "SOU",
    "Score": "2-3",
    "Away": "Liverpool",
    "AwayCode": "LIV"
  },
  {
    "Wk": 12,
    "Date": "2024-11-24",
    "Time": "16:30",
    "Home": "Ipswich Town",
    "HomeCode": "IPS",
    "Score": "1-1",
    "Away": "Manchester Utd",
    "AwayCode": "MUN"
  },
  {
    "Wk": 12,
    "Date": "2024-11-25",
    "Time": "20:00",
    "Home": "Newcastle Utd",
    "HomeCode": "NEW",
    "Score": "0-2",
    "Away": "West Ham",
    "AwayCode": "WHU"
  },
  {
    "Wk": 13,
    "Date": "2024-11-29",
    "Time": "20:00",
    "Home": "Brighton",
    "HomeCode": "BHA",
    "Score": "1-1",
    "Away": "Southampton",
    "AwayCode": "SOU"
  },
  {
    "Wk": 13,
    "Date": "2024-11-30",
    "Time": "15:00",
    "Home": "Crystal Palace",
    "HomeCode": "CRY",
    "Score": "1-1",
    "Away": "Newcastle Utd",
    "AwayCode": "NEW"
  },
  {
    "Wk": 13,
    "Date": "2024-11-30",
    "Time": "15:00",
    "Home": "Wolves",
    "HomeCode": "WOL",
    "Score": "2-4",
    "Away": "Bournemouth",
    "AwayCode": "BOU"
  },
  {
    "Wk": 13,
    "Date": "2024-11-30",
    "Time": "15:00",
    "Home": "Nott'ham Forest",
    "HomeCode": "NFO",
    "Score": "1-0",
    "Away": "Ipswich Town",
    "AwayCode": "IPS"
  },
  {
    "Wk": 13,
    "Date": "2024-11-30",
    "Time": "15:00",
    "Home": "Brentford",
    "HomeCode": "BRE",
    "Score": "4-1",
    "Away": "Leicester City",
    "AwayCode": "LEI"
  },
  {
    "Wk": 13,
    "Date": "2024-11-30",
    "Time": "17:30",
    "Home": "West Ham",
    "HomeCode": "WHU",
    "Score": "2-5",
    "Away": "Arsenal",
    "AwayCode": "ARS"
  },
  {
    "Wk": 13,
    "Date": "2024-12-01",
    "Time": "13:30",
    "Home": "Chelsea",
    "HomeCode": "CHE",
    "Score": "3-0",
    "Away": "Aston Villa",
    "AwayCode": "AVL"
  },
  {
    "Wk": 13,
    "Date": "2024-12-01",
    "Time": "13:30",
    "Home": "Tottenham",
    "HomeCode": "TOT",
    "Score": "1-1",
    "Away": "Fulham",
    "AwayCode": "FUL"
  },
  {
    "Wk": 13,
    "Date": "2024-12-01",
    "Time": "13:30",
    "Home": "Manchester Utd",
    "HomeCode": "MUN",
    "Score": "4-0",
    "Away": "Everton",
    "AwayCode": "EVE"
  },
  {
    "Wk": 13,
    "Date": "2024-12-01",
    "Time": "16:00",
    "Home": "Liverpool",
    "HomeCode": "LIV",
    "Score": "2-0",
    "Away": "Manchester City",
    "AwayCode": "MCI"
  },
  {
    "Wk": 14,
    "Date": "2024-12-03",
    "Time": "19:30",
    "Home": "Ipswich Town",
    "HomeCode": "IPS",
    "Score": "0-1",
    "Away": "Crystal Palace",
    "AwayCode": "CRY"
  },
  {
    "Wk": 14,
    "Date": "2024-12-03",
    "Time": "20:15",
    "Home": "Leicester City",
    "HomeCode": "LEI",
    "Score": "3-1",
    "Away": "West Ham",
    "AwayCode": "WHU"
  },
  {
    "Wk": 14,
    "Date": "2024-12-04",
    "Time": "19:30",
    "Home": "Everton",
    "HomeCode": "EVE",
    "Score": "4-0",
    "Away": "Wolves",
    "AwayCode": "WOL"
  },
  {
    "Wk": 14,
    "Date": "2024-12-04",
    "Time": "19:30",
    "Home": "Newcastle Utd",
    "HomeCode": "NEW",
    "Score": "3-3",
    "Away": "Liverpool",
    "AwayCode": "LIV"
  },
  {
    "Wk": 14,
    "Date": "2024-12-04",
    "Time": "19:30",
    "Home": "Manchester City",
    "HomeCode": "MCI",
    "Score": "3-0",
    "Away": "Nott'ham Forest",
    "AwayCode": "NFO"
  },
  {
    "Wk": 14,
    "Date": "2024-12-04",
    "Time": "19:30",
    "Home": "Southampton",
    "HomeCode": "SOU",
    "Score": "1-5",
    "Away": "Chelsea",
    "AwayCode": "CHE"
  },
  {
    "Wk": 14,
    "Date": "2024-12-04",
    "Time": "20:15",
    "Home": "Arsenal",
    "HomeCode": "ARS",
    "Score": "2-0",
    "Away": "Manchester Utd",
    "AwayCode": "MUN"
  },
  {
    "Wk": 14,
    "Date": "2024-12-04",
    "Time": "20:15",
    "Home": "Aston Villa",
    "HomeCode": "AVL",
    "Score": "3-1",
    "Away": "Brentford",
    "AwayCode": "BRE"
  },
  {
    "Wk": 14,
    "Date": "2024-12-05",
    "Time": "19:30",
    "Home": "Fulham",
    "HomeCode": "FUL",
    "Score": "3-1",
    "Away": "Brighton",
    "AwayCode": "BHA"
  },
  {
    "Wk": 14,
    "Date": "2024-12-05",
    "Time": "20:15",
    "Home": "Bournemouth",
    "HomeCode": "BOU",
    "Score": "1-0",
    "Away": "Tottenham",
    "AwayCode": "TOT"
  },
  {
    "Wk": 15,
    "Date": "2024-12-07",
    "Time": "15:00",
    "Home": "Brentford",
    "HomeCode": "BRE",
    "Score": "4-2",
    "Away": "Newcastle Utd",
    "AwayCode": "NEW"
  },
  {
    "Wk": 15,
    "Date": "2024-12-07",
    "Time": "15:00",
    "Home": "Crystal Palace",
    "HomeCode": "CRY",
    "Score": "2-2",
    "Away": "Manchester City",
    "AwayCode": "MCI"
  },
  {
    "Wk": 15,
    "Date": "2024-12-07",
    "Time": "15:00",
    "Home": "Aston Villa",
    "HomeCode": "AVL",
    "Score": "1-0",
    "Away": "Southampton",
    "AwayCode": "SOU"
  },
  {
    "Wk": 15,
    "Date": "2024-12-07",
    "Time": "17:30",
    "Home": "Manchester Utd",
    "HomeCode": "MUN",
    "Score": "2-3",
    "Away": "Nott'ham Forest",
    "AwayCode": "NFO"
  },
  {
    "Wk": 15,
    "Date": "2024-12-08",
    "Time": "14:00",
    "Home": "Fulham",
    "HomeCode": "FUL",
    "Score": "1-1",
    "Away": "Arsenal",
    "AwayCode": "ARS"
  },
  {
    "Wk": 15,
    "Date": "2024-12-08",
    "Time": "14:00",
    "Home": "Ipswich Town",
    "HomeCode": "IPS",
    "Score": "1-2",
    "Away": "Bournemouth",
    "AwayCode": "BOU"
  },
  {
    "Wk": 15,
    "Date": "2024-12-08",
    "Time": "14:00",
    "Home": "Leicester City",
    "HomeCode": "LEI",
    "Score": "2-2",
    "Away": "Brighton",
    "AwayCode": "BHA"
  },
  {
    "Wk": 15,
    "Date": "2024-12-08",
    "Time": "16:30",
    "Home": "Tottenham",
    "HomeCode": "TOT",
    "Score": "3-4",
    "Away": "Chelsea",
    "AwayCode": "CHE"
  },
  {
    "Wk": 15,
    "Date": "2024-12-09",
    "Time": "20:00",
    "Home": "West Ham",
    "HomeCode": "WHU",
    "Score": "2-1",
    "Away": "Wolves",
    "AwayCode": "WOL"
  },
  {
    "Wk": 16,
    "Date": "2024-12-14",
    "Time": "15:00",
    "Home": "Newcastle Utd",
    "HomeCode": "NEW",
    "Score": "4-0",
    "Away": "Leicester City",
    "AwayCode": "LEI"
  },
  {
    "Wk": 16,
    "Date": "2024-12-14",
    "Time": "15:00",
    "Home": "Arsenal",
    "HomeCode": "ARS",
    "Score": "0-0",
    "Away": "Everton",
    "AwayCode": "EVE"
  },
  {
    "Wk": 16,
    "Date": "2024-12-14",
    "Time": "15:00",
    "Home": "Wolves",
    "HomeCode": "WOL",
    "Score": "1-2",
    "Away": "Ipswich Town",
    "AwayCode": "IPS"
  },
  {
    "Wk": 16,
    "Date": "2024-12-14",
    "Time": "15:00",
    "Home": "Liverpool",
    "HomeCode": "LIV",
    "Score": "2-2",
    "Away": "Fulham",
    "AwayCode": "FUL"
  },
  {
    "Wk": 16,
    "Date": "2024-12-14",
    "Time": "17:30",
    "Home": "Nott'ham Forest",
    "HomeCode": "NFO",
    "Score": "2-1",
    "Away": "Aston Villa",
    "AwayCode": "AVL"
  },
  {
    "Wk": 16,
    "Date": "2024-12-15",
    "Time": "14:00",
    "Home": "Brighton",
    "HomeCode": "BHA",
    "Score": "1-3",
    "Away": "Crystal Palace",
    "AwayCode": "CRY"
  },
  {
    "Wk": 16,
    "Date": "2024-12-15",
    "Time": "16:30",
    "Home": "Manchester City",
    "HomeCode": "MCI",
    "Score": "1-2",
    "Away": "Manchester Utd",
    "AwayCode": "MUN"
  },
  {
    "Wk": 16,
    "Date": "2024-12-15",
    "Time": "19:00",
    "Home": "Southampton",
    "HomeCode": "SOU",
    "Score": "0-5",
    "Away": "Tottenham",
    "AwayCode": "TOT"
  },
  {
    "Wk": 16,
    "Date": "2024-12-15",
    "Time": "19:00",
    "Home": "Chelsea",
    "HomeCode": "CHE",
    "Score": "2-1",
    "Away": "Brentford",
    "AwayCode": "BRE"
  },
  {
    "Wk": 16,
    "Date": "2024-12-16",
    "Time": "20:00",
    "Home": "Bournemouth",
    "HomeCode": "BOU",
    "Score": "1-1",
    "Away": "West Ham",
    "AwayCode": "WHU"
  },
  {
    "Wk": 17,
    "Date": "2024-12-21",
    "Time": "12:30",
    "Home": "Aston Villa",
    "HomeCode": "AVL",
    "Score": "2-1",
    "Away": "Manchester City",
    "AwayCode": "MCI"
  },
  {
    "Wk": 17,
    "Date": "2024-12-21",
    "Time": "15:00",
    "Home": "West Ham",
    "HomeCode": "WHU",
    "Score": "1-1",
    "Away": "Brighton",
    "AwayCode": "BHA"
  },
  {
    "Wk": 17,
    "Date": "2024-12-21",
    "Time": "15:00",
    "Home": "Brentford",
    "HomeCode": "BRE",
    "Score": "0-2",
    "Away": "Nott'ham Forest",
    "AwayCode": "NFO"
  },
  {
    "Wk": 17,
    "Date": "2024-12-21",
    "Time": "15:00",
    "Home": "Ipswich Town",
    "HomeCode": "IPS",
    "Score": "0-4",
    "Away": "Newcastle Utd",
    "AwayCode": "NEW"
  },
  {
    "Wk": 17,
    "Date": "2024-12-21",
    "Time": "17:30",
    "Home": "Crystal Palace",
    "HomeCode": "CRY",
    "Score": "1-5",
    "Away": "Arsenal",
    "AwayCode": "ARS"
  },
  {
    "Wk": 17,
    "Date": "2024-12-22",
    "Time": "14:00",
    "Home": "Manchester Utd",
    "HomeCode": "MUN",
    "Score": "0-3",
    "Away": "Bournemouth",
    "AwayCode": "BOU"
  },
  {
    "Wk": 17,
    "Date": "2024-12-22",
    "Time": "14:00",
    "Home": "Fulham",
    "HomeCode": "FUL",
    "Score": "0-0",
    "Away": "Southampton",
    "AwayCode": "SOU"
  },
  {
    "Wk": 17,
    "Date": "2024-12-22",
    "Time": "14:00",
    "Home": "Everton",
    "HomeCode": "EVE",
    "Score": "0-0",
    "Away": "Chelsea",
    "AwayCode": "CHE"
  },
  {
    "Wk": 17,
    "Date": "2024-12-22",
    "Time": "14:00",
    "Home": "Leicester City",
    "HomeCode": "LEI",
    "Score": "0-3",
    "Away": "Wolves",
    "AwayCode": "WOL"
  },
  {
    "Wk": 17,
    "Date": "2024-12-22",
    "Time": "16:30",
    "Home": "Tottenham",
    "HomeCode": "TOT",
    "Score": "3-6",
    "Away": "Liverpool",
    "AwayCode": "LIV"
  },
  {
    "Wk": 18,
    "Date": "2024-12-26",
    "Time": "12:30",
    "Home": "Manchester City",
    "HomeCode": "MCI",
    "Score": "1-1",
    "Away": "Everton",
    "AwayCode": "EVE"
  },
  {
    "Wk": 18,
    "Date": "2024-12-26",
    "Time": "15:00",
    "Home": "Chelsea",
    "HomeCode": "CHE",
    "Score": "1-2",
    "Away": "Fulham",
    "AwayCode": "FUL"
  },
  {
    "Wk": 18,
    "Date": "2024-12-26",
    "Time": "15:00",
    "Home": "Southampton",
    "HomeCode": "SOU",
    "Score": "0-1",
    "Away": "West Ham",
    "AwayCode": "WHU"
  },
  {
    "Wk": 18,
    "Date": "2024-12-26",
    "Time": "15:00",
    "Home": "Bournemouth",
    "HomeCode": "BOU",
    "Score": "0-0",
    "Away": "Crystal Palace",
    "AwayCode": "CRY"
  },
  {
    "Wk": 18,
    "Date": "2024-12-26",
    "Time": "15:00",
    "Home": "Newcastle Utd",
    "HomeCode": "NEW",
    "Score": "3-0",
    "Away": "Aston Villa",
    "AwayCode": "AVL"
  },
  {
    "Wk": 18,
    "Date": "2024-12-26",
    "Time": "15:00",
    "Home": "Nott'ham Forest",
    "HomeCode": "NFO",
    "Score": "1-0",
    "Away": "Tottenham",
    "AwayCode": "TOT"
  },
  {
    "Wk": 18,
    "Date": "2024-12-26",
    "Time": "17:30",
    "Home": "Wolves",
    "HomeCode": "WOL",
    "Score": "2-0",
    "Away": "Manchester Utd",
    "AwayCode": "MUN"
  },
  {
    "Wk": 18,
    "Date": "2024-12-26",
    "Time": "20:00",
    "Home": "Liverpool",
    "HomeCode": "LIV",
    "Score": "3-1",
    "Away": "Leicester City",
    "AwayCode": "LEI"
  },
  {
    "Wk": 18,
    "Date": "2024-12-27",
    "Time": "19:30",
    "Home": "Brighton",
    "HomeCode": "BHA",
    "Score": "0-0",
    "Away": "Brentford",
    "AwayCode": "BRE"
  },
  {
    "Wk": 18,
    "Date": "2024-12-27",
    "Time": "20:15",
    "Home": "Arsenal",
    "HomeCode": "ARS",
    "Score": "1-0",
    "Away": "Ipswich Town",
    "AwayCode": "IPS"
  },
  {
    "Wk": 19,
    "Date": "2024-12-29",
    "Time": "14:30",
    "Home": "Leicester City",
    "HomeCode": "LEI",
    "Score": "0-2",
    "Away": "Manchester City",
    "AwayCode": "MCI"
  },
  {
    "Wk": 19,
    "Date": "2024-12-29",
    "Time": "15:00",
    "Home": "Tottenham",
    "HomeCode": "TOT",
    "Score": "2-2",
    "Away": "Wolves",
    "AwayCode": "WOL"
  },
  {
    "Wk": 19,
    "Date": "2024-12-29",
    "Time": "15:00",
    "Home": "Fulham",
    "HomeCode": "FUL",
    "Score": "2-2",
    "Away": "Bournemouth",
    "AwayCode": "BOU"
  },
  {
    "Wk": 19,
    "Date": "2024-12-29",
    "Time": "15:00",
    "Home": "Everton",
    "HomeCode": "EVE",
    "Score": "0-2",
    "Away": "Nott'ham Forest",
    "AwayCode": "NFO"
  },
  {
    "Wk": 19,
    "Date": "2024-12-29",
    "Time": "15:00",
    "Home": "Crystal Palace",
    "HomeCode": "CRY",
    "Score": "2-1",
    "Away": "Southampton",
    "AwayCode": "SOU"
  },
  {
    "Wk": 19,
    "Date": "2024-12-29",
    "Time": "17:15",
    "Home": "West Ham",
    "HomeCode": "WHU",
    "Score": "0-5",
    "Away": "Liverpool",
    "AwayCode": "LIV"
  },
  {
    "Wk": 19,
    "Date": "2024-12-30",
    "Time": "19:45",
    "Home": "Aston Villa",
    "HomeCode": "AVL",
    "Score": "2-2",
    "Away": "Brighton",
    "AwayCode": "BHA"
  },
  {
    "Wk": 19,
    "Date": "2024-12-30",
    "Time": "19:45",
    "Home": "Ipswich Town",
    "HomeCode": "IPS",
    "Score": "2-0",
    "Away": "Chelsea",
    "AwayCode": "CHE"
  },
  {
    "Wk": 19,
    "Date": "2024-12-30",
    "Time": "20:00",
    "Home": "Manchester Utd",
    "HomeCode": "MUN",
    "Score": "0-2",
    "Away": "Newcastle Utd",
    "AwayCode": "NEW"
  },
  {
    "Wk": 19,
    "Date": "2025-01-01",
    "Time": "17:30",
    "Home": "Brentford",
    "HomeCode": "BRE",
    "Score": "1-3",
    "Away": "Arsenal",
    "AwayCode": "ARS"
  },
  {
    "Wk": 20,
    "Date": "2025-01-04",
    "Time": "12:30",
    "Home": "Tottenham",
    "HomeCode": "TOT",
    "Score": "1-2",
    "Away": "Newcastle Utd",
    "AwayCode": "NEW"
  },
  {
    "Wk": 20,
    "Date": "2025-01-04",
    "Time": "15:00",
    "Home": "Southampton",
    "HomeCode": "SOU",
    "Score": "0-5",
    "Away": "Brentford",
    "AwayCode": "BRE"
  },
  {
    "Wk": 20,
    "Date": "2025-01-04",
    "Time": "15:00",
    "Home": "Bournemouth",
    "HomeCode": "BOU",
    "Score": "1-0",
    "Away": "Everton",
    "AwayCode": "EVE"
  },
  {
    "Wk": 20,
    "Date": "2025-01-04",
    "Time": "15:00",
    "Home": "Crystal Palace",
    "HomeCode": "CRY",
    "Score": "1-1",
    "Away": "Chelsea",
    "AwayCode": "CHE"
  },
  {
    "Wk": 20,
    "Date": "2025-01-04",
    "Time": "15:00",
    "Home": "Manchester City",
    "HomeCode": "MCI",
    "Score": "4-1",
    "Away": "West Ham",
    "AwayCode": "WHU"
  },
  {
    "Wk": 20,
    "Date": "2025-01-04",
    "Time": "15:00",
    "Home": "Aston Villa",
    "HomeCode": "AVL",
    "Score": "2-1",
    "Away": "Leicester City",
    "AwayCode": "LEI"
  },
  {
    "Wk": 20,
    "Date": "2025-01-04",
    "Time": "17:30",
    "Home": "Brighton",
    "HomeCode": "BHA",
    "Score": "1-1",
    "Away": "Arsenal",
    "AwayCode": "ARS"
  },
  {
    "Wk": 20,
    "Date": "2025-01-05",
    "Time": "14:00",
    "Home": "Fulham",
    "HomeCode": "FUL",
    "Score": "2-2",
    "Away": "Ipswich Town",
    "AwayCode": "IPS"
  },
  {
    "Wk": 20,
    "Date": "2025-01-05",
    "Time": "16:30",
    "Home": "Liverpool",
    "HomeCode": "LIV",
    "Score": "2-2",
    "Away": "Manchester Utd",
    "AwayCode": "MUN"
  },
  {
    "Wk": 20,
    "Date": "2025-01-06",
    "Time": "20:00",
    "Home": "Wolves",
    "HomeCode": "WOL",
    "Score": "0-3",
    "Away": "Nott'ham Forest",
    "AwayCode": "NFO"
  },
  {
    "Wk": 21,
    "Date": "2025-01-14",
    "Time": "19:30",
    "Home": "Brentford",
    "HomeCode": "BRE",
    "Score": "2-2",
    "Away": "Manchester City",
    "AwayCode": "MCI"
  },
  {
    "Wk": 21,
    "Date": "2025-01-14",
    "Time": "19:30",
    "Home": "West Ham",
    "HomeCode": "WHU",
    "Score": "3-2",
    "Away": "Fulham",
    "AwayCode": "FUL"
  },
  {
    "Wk": 21,
    "Date": "2025-01-14",
    "Time": "19:30",
    "Home": "Chelsea",
    "HomeCode": "CHE",
    "Score": "2-2",
    "Away": "Bournemouth",
    "AwayCode": "BOU"
  },
  {
    "Wk": 21,
    "Date": "2025-01-14",
    "Time": "20:00",
    "Home": "Nott'ham Forest",
    "HomeCode": "NFO",
    "Score": "1-1",
    "Away": "Liverpool",
    "AwayCode": "LIV"
  },
  {
    "Wk": 21,
    "Date": "2025-01-15",
    "Time": "19:30",
    "Home": "Everton",
    "HomeCode": "EVE",
    "Score": "0-1",
    "Away": "Aston Villa",
    "AwayCode": "AVL"
  },
  {
    "Wk": 21,
    "Date": "2025-01-15",
    "Time": "19:30",
    "Home": "Newcastle Utd",
    "HomeCode": "NEW",
    "Score": "3-0",
    "Away": "Wolves",
    "AwayCode": "WOL"
  },
  {
    "Wk": 21,
    "Date": "2025-01-15",
    "Time": "19:30",
    "Home": "Leicester City",
    "HomeCode": "LEI",
    "Score": "0-2",
    "Away": "Crystal Palace",
    "AwayCode": "CRY"
  },
  {
    "Wk": 21,
    "Date": "2025-01-15",
    "Time": "20:00",
    "Home": "Arsenal",
    "HomeCode": "ARS",
    "Score": "2-1",
    "Away": "Tottenham",
    "AwayCode": "TOT"
  },
  {
    "Wk": 21,
    "Date": "2025-01-16",
    "Time": "19:30",
    "Home": "Ipswich Town",
    "HomeCode": "IPS",
    "Score": "0-2",
    "Away": "Brighton",
    "AwayCode": "BHA"
  },
  {
    "Wk": 21,
    "Date": "2025-01-16",
    "Time": "20:00",
    "Home": "Manchester Utd",
    "HomeCode": "MUN",
    "Score": "3-1",
    "Away": "Southampton",
    "AwayCode": "SOU"
  },
  {
    "Wk": 22,
    "Date": "2025-01-18",
    "Time": "12:30",
    "Home": "Newcastle Utd",
    "HomeCode": "NEW",
    "Score": "1-4",
    "Away": "Bournemouth",
    "AwayCode": "BOU"
  },
  {
    "Wk": 22,
    "Date": "2025-01-18",
    "Time": "15:00",
    "Home": "West Ham",
    "HomeCode": "WHU",
    "Score": "0-2",
    "Away": "Crystal Palace",
    "AwayCode": "CRY"
  },
  {
    "Wk": 22,
    "Date": "2025-01-18",
    "Time": "15:00",
    "Home": "Brentford",
    "HomeCode": "BRE",
    "Score": "0-2",
    "Away": "Liverpool",
    "AwayCode": "LIV"
  },
  {
    "Wk": 22,
    "Date": "2025-01-18",
    "Time": "15:00",
    "Home": "Leicester City",
    "HomeCode": "LEI",
    "Score": "0-2",
    "Away": "Fulham",
    "AwayCode": "FUL"
  },
  {
    "Wk": 22,
    "Date": "2025-01-18",
    "Time": "17:30",
    "Home": "Arsenal",
    "HomeCode": "ARS",
    "Score": "2-2",
    "Away": "Aston Villa",
    "AwayCode": "AVL"
  },
  {
    "Wk": 22,
    "Date": "2025-01-19",
    "Time": "14:00",
    "Home": "Manchester Utd",
    "HomeCode": "MUN",
    "Score": "1-3",
    "Away": "Brighton",
    "AwayCode": "BHA"
  },
  {
    "Wk": 22,
    "Date": "2025-01-19",
    "Time": "14:00",
    "Home": "Nott'ham Forest",
    "HomeCode": "NFO",
    "Score": "3-2",
    "Away": "Southampton",
    "AwayCode": "SOU"
  },
  {
    "Wk": 22,
    "Date": "2025-01-19",
    "Time": "14:00",
    "Home": "Everton",
    "HomeCode": "EVE",
    "Score": "3-2",
    "Away": "Tottenham",
    "AwayCode": "TOT"
  },
  {
    "Wk": 22,
    "Date": "2025-01-19",
    "Time": "16:30",
    "Home": "Ipswich Town",
    "HomeCode": "IPS",
    "Score": "0-6",
    "Away": "Manchester City",
    "AwayCode": "MCI"
  },
  {
    "Wk": 22,
    "Date": "2025-01-20",
    "Time": "20:00",
    "Home": "Chelsea",
    "HomeCode": "CHE",
    "Score": "3-1",
    "Away": "Wolves",
    "AwayCode": "WOL"
  },
  {
    "Wk": 23,
    "Date": "2025-01-25",
    "Time": "15:00",
    "Home": "Wolves",
    "HomeCode": "WOL",
    "Score": "0-1",
    "Away": "Arsenal",
    "AwayCode": "ARS"
  },
  {
    "Wk": 23,
    "Date": "2025-01-25",
    "Time": "15:00",
    "Home": "Southampton",
    "HomeCode": "SOU",
    "Score": "1-3",
    "Away": "Newcastle Utd",
    "AwayCode": "NEW"
  },
  {
    "Wk": 23,
    "Date": "2025-01-25",
    "Time": "15:00",
    "Home": "Brighton",
    "HomeCode": "BHA",
    "Score": "0-1",
    "Away": "Everton",
    "AwayCode": "EVE"
  },
  {
    "Wk": 23,
    "Date": "2025-01-25",
    "Time": "15:00",
    "Home": "Liverpool",
    "HomeCode": "LIV",
    "Score": "4-1",
    "Away": "Ipswich Town",
    "AwayCode": "IPS"
  },
  {
    "Wk": 23,
    "Date": "2025-01-25",
    "Time": "15:00",
    "Home": "Bournemouth",
    "HomeCode": "BOU",
    "Score": "5-0",
    "Away": "Nott'ham Forest",
    "AwayCode": "NFO"
  },
  {
    "Wk": 23,
    "Date": "2025-01-25",
    "Time": "17:30",
    "Home": "Manchester City",
    "HomeCode": "MCI",
    "Score": "3-1",
    "Away": "Chelsea",
    "AwayCode": "CHE"
  },
  {
    "Wk": 23,
    "Date": "2025-01-26",
    "Time": "14:00",
    "Home": "Crystal Palace",
    "HomeCode": "CRY",
    "Score": "1-2",
    "Away": "Brentford",
    "AwayCode": "BRE"
  },
  {
    "Wk": 23,
    "Date": "2025-01-26",
    "Time": "14:00",
    "Home": "Tottenham",
    "HomeCode": "TOT",
    "Score": "1-2",
    "Away": "Leicester City",
    "AwayCode": "LEI"
  },
  {
    "Wk": 23,
    "Date": "2025-01-26",
    "Time": "16:30",
    "Home": "Aston Villa",
    "HomeCode": "AVL",
    "Score": "1-1",
    "Away": "West Ham",
    "AwayCode": "WHU"
  },
  {
    "Wk": 23,
    "Date": "2025-01-26",
    "Time": "19:00",
    "Home": "Fulham",
    "HomeCode": "FUL",
    "Score": "0-1",
    "Away": "Manchester Utd",
    "AwayCode": "MUN"
  },
  {
    "Wk": 24,
    "Date": "2025-02-01",
    "Time": "12:30",
    "Home": "Nott'ham Forest",
    "HomeCode": "NFO",
    "Score": "7-0",
    "Away": "Brighton",
    "AwayCode": "BHA"
  },
  {
    "Wk": 24,
    "Date": "2025-02-01",
    "Time": "15:00",
    "Home": "Ipswich Town",
    "HomeCode": "IPS",
    "Score": "1-2",
    "Away": "Southampton",
    "AwayCode": "SOU"
  },
  {
    "Wk": 24,
    "Date": "2025-02-01",
    "Time": "15:00",
    "Home": "Everton",
    "HomeCode": "EVE",
    "Score": "4-0",
    "Away": "Leicester City",
    "AwayCode": "LEI"
  },
  {
    "Wk": 24,
    "Date": "2025-02-01",
    "Time": "15:00",
    "Home": "Newcastle Utd",
    "HomeCode": "NEW",
    "Score": "1-2",
    "Away": "Fulham",
    "AwayCode": "FUL"
  },
  {
    "Wk": 24,
    "Date": "2025-02-01",
    "Time": "15:00",
    "Home": "Bournemouth",
    "HomeCode": "BOU",
    "Score": "0-2",
    "Away": "Liverpool",
    "AwayCode": "LIV"
  },
  {
    "Wk": 24,
    "Date": "2025-02-01",
    "Time": "17:30",
    "Home": "Wolves",
    "HomeCode": "WOL",
    "Score": "2-0",
    "Away": "Aston Villa",
    "AwayCode": "AVL"
  },
  {
    "Wk": 24,
    "Date": "2025-02-02",
    "Time": "14:00",
    "Home": "Brentford",
    "HomeCode": "BRE",
    "Score": "0-2",
    "Away": "Tottenham",
    "AwayCode": "TOT"
  },
  {
    "Wk": 24,
    "Date": "2025-02-02",
    "Time": "14:00",
    "Home": "Manchester Utd",
    "HomeCode": "MUN",
    "Score": "0-2",
    "Away": "Crystal Palace",
    "AwayCode": "CRY"
  },
  {
    "Wk": 24,
    "Date": "2025-02-02",
    "Time": "16:30",
    "Home": "Arsenal",
    "HomeCode": "ARS",
    "Score": "5-1",
    "Away": "Manchester City",
    "AwayCode": "MCI"
  },
  {
    "Wk": 24,
    "Date": "2025-02-03",
    "Time": "20:00",
    "Home": "Chelsea",
    "HomeCode": "CHE",
    "Score": "2-1",
    "Away": "West Ham",
    "AwayCode": "WHU"
  },
  {
    "Wk": 15,
    "Date": "2025-02-12",
    "Time": "19:30",
    "Home": "Everton",
    "HomeCode": "EVE",
    "Score": "2-2",
    "Away": "Liverpool",
    "AwayCode": "LIV"
  },
  {
    "Wk": 25,
    "Date": "2025-02-14",
    "Time": "20:00",
    "Home": "Brighton",
    "HomeCode": "BHA",
    "Score": "3-0",
    "Away": "Chelsea",
    "AwayCode": "CHE"
  },
  {
    "Wk": 25,
    "Date": "2025-02-15",
    "Time": "12:30",
    "Home": "Leicester City",
    "HomeCode": "LEI",
    "Score": "0-2",
    "Away": "Arsenal",
    "AwayCode": "ARS"
  },
  {
    "Wk": 25,
    "Date": "2025-02-15",
    "Time": "15:00",
    "Home": "Aston Villa",
    "HomeCode": "AVL",
    "Score": "1-1",
    "Away": "Ipswich Town",
    "AwayCode": "IPS"
  },
  {
    "Wk": 25,
    "Date": "2025-02-15",
    "Time": "15:00",
    "Home": "Fulham",
    "HomeCode": "FUL",
    "Score": "2-1",
    "Away": "Nott'ham Forest",
    "AwayCode": "NFO"
  },
  {
    "Wk": 25,
    "Date": "2025-02-15",
    "Time": "15:00",
    "Home": "West Ham",
    "HomeCode": "WHU",
    "Score": "0-1",
    "Away": "Brentford",
    "AwayCode": "BRE"
  },
  {
    "Wk": 25,
    "Date": "2025-02-15",
    "Time": "15:00",
    "Home": "Manchester City",
    "HomeCode": "MCI",
    "Score": "4-0",
    "Away": "Newcastle Utd",
    "AwayCode": "NEW"
  },
  {
    "Wk": 25,
    "Date": "2025-02-15",
    "Time": "15:00",
    "Home": "Southampton",
    "HomeCode": "SOU",
    "Score": "1-3",
    "Away": "Bournemouth",
    "AwayCode": "BOU"
  },
  {
    "Wk": 25,
    "Date": "2025-02-15",
    "Time": "17:30",
    "Home": "Crystal Palace",
    "HomeCode": "CRY",
    "Score": "1-2",
    "Away": "Everton",
    "AwayCode": "EVE"
  },
  {
    "Wk": 25,
    "Date": "2025-02-16",
    "Time": "14:00",
    "Home": "Liverpool",
    "HomeCode": "LIV",
    "Score": "2-1",
    "Away": "Wolves",
    "AwayCode": "WOL"
  },
  {
    "Wk": 25,
    "Date": "2025-02-16",
    "Time": "16:30",
    "Home": "Tottenham",
    "HomeCode": "TOT",
    "Score": "1-0",
    "Away": "Manchester Utd",
    "AwayCode": "MUN"
  },
  {
    "Wk": 29,
    "Date": "2025-02-19",
    "Time": "19:30",
    "Home": "Aston Villa",
    "HomeCode": "AVL",
    "Score": "2-2",
    "Away": "Liverpool",
    "AwayCode": "LIV"
  },
  {
    "Wk": 26,
    "Date": "2025-02-21",
    "Time": "20:00",
    "Home": "Leicester City",
    "HomeCode": "LEI",
    "Score": "0-4",
    "Away": "Brentford",
    "AwayCode": "BRE"
  },
  {
    "Wk": 26,
    "Date": "2025-02-22",
    "Time": "12:30",
    "Home": "Everton",
    "HomeCode": "EVE",
    "Score": "2-2",
    "Away": "Manchester Utd",
    "AwayCode": "MUN"
  },
  {
    "Wk": 26,
    "Date": "2025-02-22",
    "Time": "15:00",
    "Home": "Fulham",
    "HomeCode": "FUL",
    "Score": "0-2",
    "Away": "Crystal Palace",
    "AwayCode": "CRY"
  },
  {
    "Wk": 26,
    "Date": "2025-02-22",
    "Time": "15:00",
    "Home": "Ipswich Town",
    "HomeCode": "IPS",
    "Score": "1-4",
    "Away": "Tottenham",
    "AwayCode": "TOT"
  },
  {
    "Wk": 26,
    "Date": "2025-02-22",
    "Time": "15:00",
    "Home": "Bournemouth",
    "HomeCode": "BOU",
    "Score": "0-1",
    "Away": "Wolves",
    "AwayCode": "WOL"
  },
  {
    "Wk": 26,
    "Date": "2025-02-22",
    "Time": "15:00",
    "Home": "Arsenal",
    "HomeCode": "ARS",
    "Score": "0-1",
    "Away": "West Ham",
    "AwayCode": "WHU"
  },
  {
    "Wk": 26,
    "Date": "2025-02-22",
    "Time": "15:00",
    "Home": "Southampton",
    "HomeCode": "SOU",
    "Score": "0-4",
    "Away": "Brighton",
    "AwayCode": "BHA"
  },
  {
    "Wk": 26,
    "Date": "2025-02-22",
    "Time": "17:30",
    "Home": "Aston Villa",
    "HomeCode": "AVL",
    "Score": "2-1",
    "Away": "Chelsea",
    "AwayCode": "CHE"
  },
  {
    "Wk": 26,
    "Date": "2025-02-23",
    "Time": "14:00",
    "Home": "Newcastle Utd",
    "HomeCode": "NEW",
    "Score": "4-3",
    "Away": "Nott'ham Forest",
    "AwayCode": "NFO"
  },
  {
    "Wk": 26,
    "Date": "2025-02-23",
    "Time": "16:30",
    "Home": "Manchester City",
    "HomeCode": "MCI",
    "Score": "0-2",
    "Away": "Liverpool",
    "AwayCode": "LIV"
  },
  {
    "Wk": 27,
    "Date": "2025-02-25",
    "Time": "19:30",
    "Home": "Crystal Palace",
    "HomeCode": "CRY",
    "Score": "4-1",
    "Away": "Aston Villa",
    "AwayCode": "AVL"
  },
  {
    "Wk": 27,
    "Date": "2025-02-25",
    "Time": "19:30",
    "Home": "Wolves",
    "HomeCode": "WOL",
    "Score": "1-2",
    "Away": "Fulham",
    "AwayCode": "FUL"
  },
  {
    "Wk": 27,
    "Date": "2025-02-25",
    "Time": "19:30",
    "Home": "Brighton",
    "HomeCode": "BHA",
    "Score": "2-1",
    "Away": "Bournemouth",
    "AwayCode": "BOU"
  },
  {
    "Wk": 27,
    "Date": "2025-02-25",
    "Time": "20:15",
    "Home": "Chelsea",
    "HomeCode": "CHE",
    "Score": "4-0",
    "Away": "Southampton",
    "AwayCode": "SOU"
  },
  {
    "Wk": 27,
    "Date": "2025-02-26",
    "Time": "19:30",
    "Home": "Brentford",
    "HomeCode": "BRE",
    "Score": "1-1",
    "Away": "Everton",
    "AwayCode": "EVE"
  },
  {
    "Wk": 27,
    "Date": "2025-02-26",
    "Time": "19:30",
    "Home": "Tottenham",
    "HomeCode": "TOT",
    "Score": "0-1",
    "Away": "Manchester City",
    "AwayCode": "MCI"
  },
  {
    "Wk": 27,
    "Date": "2025-02-26",
    "Time": "19:30",
    "Home": "Manchester Utd",
    "HomeCode": "MUN",
    "Score": "3-2",
    "Away": "Ipswich Town",
    "AwayCode": "IPS"
  },
  {
    "Wk": 27,
    "Date": "2025-02-26",
    "Time": "19:30",
    "Home": "Nott'ham Forest",
    "HomeCode": "NFO",
    "Score": "0-0",
    "Away": "Arsenal",
    "AwayCode": "ARS"
  },
  {
    "Wk": 27,
    "Date": "2025-02-26",
    "Time": "20:15",
    "Home": "Liverpool",
    "HomeCode": "LIV",
    "Score": "2-0",
    "Away": "Newcastle Utd",
    "AwayCode": "NEW"
  },
  {
    "Wk": 27,
    "Date": "2025-02-27",
    "Time": "20:00",
    "Home": "West Ham",
    "HomeCode": "WHU",
    "Score": "2-0",
    "Away": "Leicester City",
    "AwayCode": "LEI"
  },
  {
    "Wk": 28,
    "Date": "2025-03-08",
    "Time": "12:30",
    "Home": "Nott'ham Forest",
    "HomeCode": "NFO",
    "Score": "",
    "Away": "Manchester City",
    "AwayCode": "MCI"
  },
  {
    "Wk": 28,
    "Date": "2025-03-08",
    "Time": "15:00",
    "Home": "Liverpool",
    "HomeCode": "LIV",
    "Score": "",
    "Away": "Southampton",
    "AwayCode": "SOU"
  },
  {
    "Wk": 28,
    "Date": "2025-03-08",
    "Time": "15:00",
    "Home": "Crystal Palace",
    "HomeCode": "CRY",
    "Score": "",
    "Away": "Ipswich Town",
    "AwayCode": "IPS"
  },
  {
    "Wk": 28,
    "Date": "2025-03-08",
    "Time": "15:00",
    "Home": "Brighton",
    "HomeCode": "BHA",
    "Score": "",
    "Away": "Fulham",
    "AwayCode": "FUL"
  },
  {
    "Wk": 28,
    "Date": "2025-03-08",
    "Time": "17:30",
    "Home": "Brentford",
    "HomeCode": "BRE",
    "Score": "",
    "Away": "Aston Villa",
    "AwayCode": "AVL"
  },
  {
    "Wk": 28,
    "Date": "2025-03-08",
    "Time": "20:00",
    "Home": "Wolves",
    "HomeCode": "WOL",
    "Score": "",
    "Away": "Everton",
    "AwayCode": "EVE"
  },
  {
    "Wk": 28,
    "Date": "2025-03-09",
    "Time": "14:00",
    "Home": "Chelsea",
    "HomeCode": "CHE",
    "Score": "",
    "Away": "Leicester City",
    "AwayCode": "LEI"
  },
  {
    "Wk": 28,
    "Date": "2025-03-09",
    "Time": "14:00",
    "Home": "Tottenham",
    "HomeCode": "TOT",
    "Score": "",
    "Away": "Bournemouth",
    "AwayCode": "BOU"
  },
  {
    "Wk": 28,
    "Date": "2025-03-09",
    "Time": "16:30",
    "Home": "Manchester Utd",
    "HomeCode": "MUN",
    "Score": "",
    "Away": "Arsenal",
    "AwayCode": "ARS"
  },
  {
    "Wk": 28,
    "Date": "2025-03-10",
    "Time": "20:00",
    "Home": "West Ham",
    "HomeCode": "WHU",
    "Score": "",
    "Away": "Newcastle Utd",
    "AwayCode": "NEW"
  },
  {
    "Wk": 29,
    "Date": "2025-03-15",
    "Time": "15:00",
    "Home": "Manchester City",
    "HomeCode": "MCI",
    "Score": "",
    "Away": "Brighton",
    "AwayCode": "BHA"
  },
  {
    "Wk": 29,
    "Date": "2025-03-15",
    "Time": "15:00",
    "Home": "Ipswich Town",
    "HomeCode": "IPS",
    "Score": "",
    "Away": "Nott'ham Forest",
    "AwayCode": "NFO"
  },
  {
    "Wk": 29,
    "Date": "2025-03-15",
    "Time": "15:00",
    "Home": "Everton",
    "HomeCode": "EVE",
    "Score": "",
    "Away": "West Ham",
    "AwayCode": "WHU"
  },
  {
    "Wk": 29,
    "Date": "2025-03-15",
    "Time": "15:00",
    "Home": "Southampton",
    "HomeCode": "SOU",
    "Score": "",
    "Away": "Wolves",
    "AwayCode": "WOL"
  },
  {
    "Wk": 29,
    "Date": "2025-03-15",
    "Time": "17:30",
    "Home": "Bournemouth",
    "HomeCode": "BOU",
    "Score": "",
    "Away": "Brentford",
    "AwayCode": "BRE"
  },
  {
    "Wk": 29,
    "Date": "2025-03-16",
    "Time": "13:30",
    "Home": "Arsenal",
    "HomeCode": "ARS",
    "Score": "",
    "Away": "Chelsea",
    "AwayCode": "CHE"
  },
  {
    "Wk": 29,
    "Date": "2025-03-16",
    "Time": "13:30",
    "Home": "Fulham",
    "HomeCode": "FUL",
    "Score": "",
    "Away": "Tottenham",
    "AwayCode": "TOT"
  },
  {
    "Wk": 29,
    "Date": "2025-03-16",
    "Time": "19:00",
    "Home": "Leicester City",
    "HomeCode": "LEI",
    "Score": "",
    "Away": "Manchester Utd",
    "AwayCode": "MUN"
  },
  {
    "Wk": 30,
    "Date": "2025-04-01",
    "Time": "19:45",
    "Home": "Brighton",
    "HomeCode": "BHA",
    "Score": "",
    "Away": "Aston Villa",
    "AwayCode": "AVL"
  },
  {
    "Wk": 30,
    "Date": "2025-04-01",
    "Time": "19:45",
    "Home": "Bournemouth",
    "HomeCode": "BOU",
    "Score": "",
    "Away": "Ipswich Town",
    "AwayCode": "IPS"
  },
  {
    "Wk": 30,
    "Date": "2025-04-01",
    "Time": "19:45",
    "Home": "Wolves",
    "HomeCode": "WOL",
    "Score": "",
    "Away": "West Ham",
    "AwayCode": "WHU"
  },
  {
    "Wk": 30,
    "Date": "2025-04-01",
    "Time": "19:45",
    "Home": "Arsenal",
    "HomeCode": "ARS",
    "Score": "",
    "Away": "Fulham",
    "AwayCode": "FUL"
  },
  {
    "Wk": 30,
    "Date": "2025-04-01",
    "Time": "20:00",
    "Home": "Nott'ham Forest",
    "HomeCode": "NFO",
    "Score": "",
    "Away": "Manchester Utd",
    "AwayCode": "MUN"
  },
  {
    "Wk": 30,
    "Date": "2025-04-02",
    "Time": "19:45",
    "Home": "Southampton",
    "HomeCode": "SOU",
    "Score": "",
    "Away": "Crystal Palace",
    "AwayCode": "CRY"
  },
  {
    "Wk": 30,
    "Date": "2025-04-02",
    "Time": "19:45",
    "Home": "Manchester City",
    "HomeCode": "MCI",
    "Score": "",
    "Away": "Leicester City",
    "AwayCode": "LEI"
  },
  {
    "Wk": 30,
    "Date": "2025-04-02",
    "Time": "19:45",
    "Home": "Newcastle Utd",
    "HomeCode": "NEW",
    "Score": "",
    "Away": "Brentford",
    "AwayCode": "BRE"
  },
  {
    "Wk": 30,
    "Date": "2025-04-02",
    "Time": "20:00",
    "Home": "Liverpool",
    "HomeCode": "LIV",
    "Score": "",
    "Away": "Everton",
    "AwayCode": "EVE"
  },
  {
    "Wk": 30,
    "Date": "2025-04-03",
    "Time": "20:00",
    "Home": "Chelsea",
    "HomeCode": "CHE",
    "Score": "",
    "Away": "Tottenham",
    "AwayCode": "TOT"
  },
  {
    "Wk": 31,
    "Date": "2025-04-05",
    "Time": "12:30",
    "Home": "Everton",
    "HomeCode": "EVE",
    "Score": "",
    "Away": "Arsenal",
    "AwayCode": "ARS"
  },
  {
    "Wk": 31,
    "Date": "2025-04-05",
    "Time": "15:00",
    "Home": "West Ham",
    "HomeCode": "WHU",
    "Score": "",
    "Away": "Bournemouth",
    "AwayCode": "BOU"
  },
  {
    "Wk": 31,
    "Date": "2025-04-05",
    "Time": "15:00",
    "Home": "Ipswich Town",
    "HomeCode": "IPS",
    "Score": "",
    "Away": "Wolves",
    "AwayCode": "WOL"
  },
  {
    "Wk": 31,
    "Date": "2025-04-05",
    "Time": "15:00",
    "Home": "Crystal Palace",
    "HomeCode": "CRY",
    "Score": "",
    "Away": "Brighton",
    "AwayCode": "BHA"
  },
  {
    "Wk": 31,
    "Date": "2025-04-05",
    "Time": "17:30",
    "Home": "Aston Villa",
    "HomeCode": "AVL",
    "Score": "",
    "Away": "Nott'ham Forest",
    "AwayCode": "NFO"
  },
  {
    "Wk": 31,
    "Date": "2025-04-06",
    "Time": "14:00",
    "Home": "Brentford",
    "HomeCode": "BRE",
    "Score": "",
    "Away": "Chelsea",
    "AwayCode": "CHE"
  },
  {
    "Wk": 31,
    "Date": "2025-04-06",
    "Time": "14:00",
    "Home": "Fulham",
    "HomeCode": "FUL",
    "Score": "",
    "Away": "Liverpool",
    "AwayCode": "LIV"
  },
  {
    "Wk": 31,
    "Date": "2025-04-06",
    "Time": "14:00",
    "Home": "Tottenham",
    "HomeCode": "TOT",
    "Score": "",
    "Away": "Southampton",
    "AwayCode": "SOU"
  },
  {
    "Wk": 31,
    "Date": "2025-04-06",
    "Time": "16:30",
    "Home": "Manchester Utd",
    "HomeCode": "MUN",
    "Score": "",
    "Away": "Manchester City",
    "AwayCode": "MCI"
  },
  {
    "Wk": 31,
    "Date": "2025-04-07",
    "Time": "20:00",
    "Home": "Leicester City",
    "HomeCode": "LEI",
    "Score": "",
    "Away": "Newcastle Utd",
    "AwayCode": "NEW"
  },
  {
    "Wk": 32,
    "Date": "2025-04-12",
    "Time": "12:30",
    "Home": "Manchester City",
    "HomeCode": "MCI",
    "Score": "",
    "Away": "Crystal Palace",
    "AwayCode": "CRY"
  },
  {
    "Wk": 32,
    "Date": "2025-04-12",
    "Time": "15:00",
    "Home": "Wolves",
    "HomeCode": "WOL",
    "Score": "",
    "Away": "Tottenham",
    "AwayCode": "TOT"
  },
  {
    "Wk": 32,
    "Date": "2025-04-12",
    "Time": "15:00",
    "Home": "Brighton",
    "HomeCode": "BHA",
    "Score": "",
    "Away": "Leicester City",
    "AwayCode": "LEI"
  },
  {
    "Wk": 32,
    "Date": "2025-04-12",
    "Time": "15:00",
    "Home": "Nott'ham Forest",
    "HomeCode": "NFO",
    "Score": "",
    "Away": "Everton",
    "AwayCode": "EVE"
  },
  {
    "Wk": 32,
    "Date": "2025-04-12",
    "Time": "15:00",
    "Home": "Chelsea",
    "HomeCode": "CHE",
    "Score": "",
    "Away": "Ipswich Town",
    "AwayCode": "IPS"
  },
  {
    "Wk": 32,
    "Date": "2025-04-12",
    "Time": "15:00",
    "Home": "Southampton",
    "HomeCode": "SOU",
    "Score": "",
    "Away": "Aston Villa",
    "AwayCode": "AVL"
  },
  {
    "Wk": 32,
    "Date": "2025-04-12",
    "Time": "17:30",
    "Home": "Arsenal",
    "HomeCode": "ARS",
    "Score": "",
    "Away": "Brentford",
    "AwayCode": "BRE"
  },
  {
    "Wk": 32,
    "Date": "2025-04-13",
    "Time": "14:00",
    "Home": "Liverpool",
    "HomeCode": "LIV",
    "Score": "",
    "Away": "West Ham",
    "AwayCode": "WHU"
  },
  {
    "Wk": 32,
    "Date": "2025-04-13",
    "Time": "16:30",
    "Home": "Newcastle Utd",
    "HomeCode": "NEW",
    "Score": "",
    "Away": "Manchester Utd",
    "AwayCode": "MUN"
  },
  {
    "Wk": 32,
    "Date": "2025-04-14",
    "Time": "20:00",
    "Home": "Bournemouth",
    "HomeCode": "BOU",
    "Score": "",
    "Away": "Fulham",
    "AwayCode": "FUL"
  },
  {
    "Wk": 29,
    "Date": "2025-04-16",
    "Time": "19:30",
    "Home": "Newcastle Utd",
    "HomeCode": "NEW",
    "Score": "",
    "Away": "Crystal Palace",
    "AwayCode": "CRY"
  },
  {
    "Wk": 33,
    "Date": "2025-04-19",
    "Time": "15:00",
    "Home": "Brentford",
    "HomeCode": "BRE",
    "Score": "",
    "Away": "Brighton",
    "AwayCode": "BHA"
  },
  {
    "Wk": 33,
    "Date": "2025-04-19",
    "Time": "15:00",
    "Home": "West Ham",
    "HomeCode": "WHU",
    "Score": "",
    "Away": "Southampton",
    "AwayCode": "SOU"
  },
  {
    "Wk": 33,
    "Date": "2025-04-19",
    "Time": "15:00",
    "Home": "Crystal Palace",
    "HomeCode": "CRY",
    "Score": "",
    "Away": "Bournemouth",
    "AwayCode": "BOU"
  },
  {
    "Wk": 33,
    "Date": "2025-04-19",
    "Time": "15:00",
    "Home": "Everton",
    "HomeCode": "EVE",
    "Score": "",
    "Away": "Manchester City",
    "AwayCode": "MCI"
  },
  {
    "Wk": 33,
    "Date": "2025-04-19",
    "Time": "15:00",
    "Home": "Fulham",
    "HomeCode": "FUL",
    "Score": "",
    "Away": "Chelsea",
    "AwayCode": "CHE"
  },
  {
    "Wk": 33,
    "Date": "2025-04-19",
    "Time": "15:00",
    "Home": "Manchester Utd",
    "HomeCode": "MUN",
    "Score": "",
    "Away": "Wolves",
    "AwayCode": "WOL"
  },
  {
    "Wk": 33,
    "Date": "2025-04-19",
    "Time": "17:30",
    "Home": "Aston Villa",
    "HomeCode": "AVL",
    "Score": "",
    "Away": "Newcastle Utd",
    "AwayCode": "NEW"
  },
  {
    "Wk": 33,
    "Date": "2025-04-20",
    "Time": "14:00",
    "Home": "Ipswich Town",
    "HomeCode": "IPS",
    "Score": "",
    "Away": "Arsenal",
    "AwayCode": "ARS"
  },
  {
    "Wk": 33,
    "Date": "2025-04-20",
    "Time": "16:30",
    "Home": "Leicester City",
    "HomeCode": "LEI",
    "Score": "",
    "Away": "Liverpool",
    "AwayCode": "LIV"
  },
  {
    "Wk": 33,
    "Date": "2025-04-21",
    "Time": "20:00",
    "Home": "Tottenham",
    "HomeCode": "TOT",
    "Score": "",
    "Away": "Nott'ham Forest",
    "AwayCode": "NFO"
  },
  {
    "Wk": 34,
    "Date": "2025-04-26",
    "Time": "12:30",
    "Home": "Chelsea",
    "HomeCode": "CHE",
    "Score": "",
    "Away": "Everton",
    "AwayCode": "EVE"
  },
  {
    "Wk": 34,
    "Date": "2025-04-26",
    "Time": "15:00",
    "Home": "Wolves",
    "HomeCode": "WOL",
    "Score": "",
    "Away": "Leicester City",
    "AwayCode": "LEI"
  },
  {
    "Wk": 34,
    "Date": "2025-04-26",
    "Time": "15:00",
    "Home": "Newcastle Utd",
    "HomeCode": "NEW",
    "Score": "",
    "Away": "Ipswich Town",
    "AwayCode": "IPS"
  },
  {
    "Wk": 34,
    "Date": "2025-04-26",
    "Time": "15:00",
    "Home": "Southampton",
    "HomeCode": "SOU",
    "Score": "",
    "Away": "Fulham",
    "AwayCode": "FUL"
  },
  {
    "Wk": 34,
    "Date": "2025-04-26",
    "Time": "15:00",
    "Home": "Nott'ham Forest",
    "HomeCode": "NFO",
    "Score": "",
    "Away": "Brentford",
    "AwayCode": "BRE"
  },
  {
    "Wk": 34,
    "Date": "2025-04-26",
    "Time": "15:00",
    "Home": "Brighton",
    "HomeCode": "BHA",
    "Score": "",
    "Away": "West Ham",
    "AwayCode": "WHU"
  },
  {
    "Wk": 34,
    "Date": "2025-04-26",
    "Time": "17:30",
    "Home": "Arsenal",
    "HomeCode": "ARS",
    "Score": "",
    "Away": "Crystal Palace",
    "AwayCode": "CRY"
  },
  {
    "Wk": 34,
    "Date": "2025-04-27",
    "Time": "14:00",
    "Home": "Bournemouth",
    "HomeCode": "BOU",
    "Score": "",
    "Away": "Manchester Utd",
    "AwayCode": "MUN"
  },
  {
    "Wk": 34,
    "Date": "2025-04-27",
    "Time": "16:30",
    "Home": "Liverpool",
    "HomeCode": "LIV",
    "Score": "",
    "Away": "Tottenham",
    "AwayCode": "TOT"
  },
  {
    "Wk": 34,
    "Date": "2025-04-28",
    "Time": "20:00",
    "Home": "Manchester City",
    "HomeCode": "MCI",
    "Score": "",
    "Away": "Aston Villa",
    "AwayCode": "AVL"
  },
  {
    "Wk": 35,
    "Date": "2025-05-03",
    "Time": "15:00",
    "Home": "Chelsea",
    "HomeCode": "CHE",
    "Score": "",
    "Away": "Liverpool",
    "AwayCode": "LIV"
  },
  {
    "Wk": 35,
    "Date": "2025-05-03",
    "Time": "15:00",
    "Home": "Brentford",
    "HomeCode": "BRE",
    "Score": "",
    "Away": "Manchester Utd",
    "AwayCode": "MUN"
  },
  {
    "Wk": 35,
    "Date": "2025-05-03",
    "Time": "15:00",
    "Home": "Manchester City",
    "HomeCode": "MCI",
    "Score": "",
    "Away": "Wolves",
    "AwayCode": "WOL"
  },
  {
    "Wk": 35,
    "Date": "2025-05-03",
    "Time": "15:00",
    "Home": "West Ham",
    "HomeCode": "WHU",
    "Score": "",
    "Away": "Tottenham",
    "AwayCode": "TOT"
  },
  {
    "Wk": 35,
    "Date": "2025-05-03",
    "Time": "15:00",
    "Home": "Crystal Palace",
    "HomeCode": "CRY",
    "Score": "",
    "Away": "Nott'ham Forest",
    "AwayCode": "NFO"
  },
  {
    "Wk": 35,
    "Date": "2025-05-03",
    "Time": "15:00",
    "Home": "Arsenal",
    "HomeCode": "ARS",
    "Score": "",
    "Away": "Bournemouth",
    "AwayCode": "BOU"
  },
  {
    "Wk": 35,
    "Date": "2025-05-03",
    "Time": "15:00",
    "Home": "Everton",
    "HomeCode": "EVE",
    "Score": "",
    "Away": "Ipswich Town",
    "AwayCode": "IPS"
  },
  {
    "Wk": 35,
    "Date": "2025-05-03",
    "Time": "15:00",
    "Home": "Aston Villa",
    "HomeCode": "AVL",
    "Score": "",
    "Away": "Fulham",
    "AwayCode": "FUL"
  },
  {
    "Wk": 35,
    "Date": "2025-05-03",
    "Time": "15:00",
    "Home": "Brighton",
    "HomeCode": "BHA",
    "Score": "",
    "Away": "Newcastle Utd",
    "AwayCode": "NEW"
  },
  {
    "Wk": 35,
    "Date": "2025-05-03",
    "Time": "15:00",
    "Home": "Leicester City",
    "HomeCode": "LEI",
    "Score": "",
    "Away": "Southampton",
    "AwayCode": "SOU"
  },
  {
    "Wk": 36,
    "Date": "2025-05-10",
    "Time": "15:00",
    "Home": "Liverpool",
    "HomeCode": "LIV",
    "Score": "",
    "Away": "Arsenal",
    "AwayCode": "ARS"
  },
  {
    "Wk": 36,
    "Date": "2025-05-10",
    "Time": "15:00",
    "Home": "Southampton",
    "HomeCode": "SOU",
    "Score": "",
    "Away": "Manchester City",
    "AwayCode": "MCI"
  },
  {
    "Wk": 36,
    "Date": "2025-05-10",
    "Time": "15:00",
    "Home": "Tottenham",
    "HomeCode": "TOT",
    "Score": "",
    "Away": "Crystal Palace",
    "AwayCode": "CRY"
  },
  {
    "Wk": 36,
    "Date": "2025-05-10",
    "Time": "15:00",
    "Home": "Fulham",
    "HomeCode": "FUL",
    "Score": "",
    "Away": "Everton",
    "AwayCode": "EVE"
  },
  {
    "Wk": 36,
    "Date": "2025-05-10",
    "Time": "15:00",
    "Home": "Newcastle Utd",
    "HomeCode": "NEW",
    "Score": "",
    "Away": "Chelsea",
    "AwayCode": "CHE"
  },
  {
    "Wk": 36,
    "Date": "2025-05-10",
    "Time": "15:00",
    "Home": "Nott'ham Forest",
    "HomeCode": "NFO",
    "Score": "",
    "Away": "Leicester City",
    "AwayCode": "LEI"
  },
  {
    "Wk": 36,
    "Date": "2025-05-10",
    "Time": "15:00",
    "Home": "Manchester Utd",
    "HomeCode": "MUN",
    "Score": "",
    "Away": "West Ham",
    "AwayCode": "WHU"
  },
  {
    "Wk": 36,
    "Date": "2025-05-10",
    "Time": "15:00",
    "Home": "Bournemouth",
    "HomeCode": "BOU",
    "Score": "",
    "Away": "Aston Villa",
    "AwayCode": "AVL"
  },
  {
    "Wk": 36,
    "Date": "2025-05-10",
    "Time": "15:00",
    "Home": "Ipswich Town",
    "HomeCode": "IPS",
    "Score": "",
    "Away": "Brentford",
    "AwayCode": "BRE"
  },
  {
    "Wk": 36,
    "Date": "2025-05-10",
    "Time": "15:00",
    "Home": "Wolves",
    "HomeCode": "WOL",
    "Score": "",
    "Away": "Brighton",
    "AwayCode": "BHA"
  },
  {
    "Wk": 37,
    "Date": "2025-05-18",
    "Time": "15:00",
    "Home": "Brentford",
    "HomeCode": "BRE",
    "Score": "",
    "Away": "Fulham",
    "AwayCode": "FUL"
  },
  {
    "Wk": 37,
    "Date": "2025-05-18",
    "Time": "15:00",
    "Home": "Arsenal",
    "HomeCode": "ARS",
    "Score": "",
    "Away": "Newcastle Utd",
    "AwayCode": "NEW"
  },
  {
    "Wk": 37,
    "Date": "2025-05-18",
    "Time": "15:00",
    "Home": "Brighton",
    "HomeCode": "BHA",
    "Score": "",
    "Away": "Liverpool",
    "AwayCode": "LIV"
  },
  {
    "Wk": 37,
    "Date": "2025-05-18",
    "Time": "15:00",
    "Home": "Leicester City",
    "HomeCode": "LEI",
    "Score": "",
    "Away": "Ipswich Town",
    "AwayCode": "IPS"
  },
  {
    "Wk": 37,
    "Date": "2025-05-18",
    "Time": "15:00",
    "Home": "West Ham",
    "HomeCode": "WHU",
    "Score": "",
    "Away": "Nott'ham Forest",
    "AwayCode": "NFO"
  },
  {
    "Wk": 37,
    "Date": "2025-05-18",
    "Time": "15:00",
    "Home": "Everton",
    "HomeCode": "EVE",
    "Score": "",
    "Away": "Southampton",
    "AwayCode": "SOU"
  },
  {
    "Wk": 37,
    "Date": "2025-05-18",
    "Time": "15:00",
    "Home": "Aston Villa",
    "HomeCode": "AVL",
    "Score": "",
    "Away": "Tottenham",
    "AwayCode": "TOT"
  },
  {
    "Wk": 37,
    "Date": "2025-05-18",
    "Time": "15:00",
    "Home": "Chelsea",
    "HomeCode": "CHE",
    "Score": "",
    "Away": "Manchester Utd",
    "AwayCode": "MUN"
  },
  {
    "Wk": 37,
    "Date": "2025-05-18",
    "Time": "15:00",
    "Home": "Manchester City",
    "HomeCode": "MCI",
    "Score": "",
    "Away": "Bournemouth",
    "AwayCode": "BOU"
  },
  {
    "Wk": 37,
    "Date": "2025-05-18",
    "Time": "15:00",
    "Home": "Crystal Palace",
    "HomeCode": "CRY",
    "Score": "",
    "Away": "Wolves",
    "AwayCode": "WOL"
  },
  {
    "Wk": 38,
    "Date": "2025-05-25",
    "Time": "16:00",
    "Home": "Southampton",
    "HomeCode": "SOU",
    "Score": "",
    "Away": "Arsenal",
    "AwayCode": "ARS"
  },
  {
    "Wk": 38,
    "Date": "2025-05-25",
    "Time": "16:00",
    "Home": "Liverpool",
    "HomeCode": "LIV",
    "Score": "",
    "Away": "Crystal Palace",
    "AwayCode": "CRY"
  },
  {
    "Wk": 38,
    "Date": "2025-05-25",
    "Time": "16:00",
    "Home": "Ipswich Town",
    "HomeCode": "IPS",
    "Score": "",
    "Away": "West Ham",
    "AwayCode": "WHU"
  },
  {
    "Wk": 38,
    "Date": "2025-05-25",
    "Time": "16:00",
    "Home": "Bournemouth",
    "HomeCode": "BOU",
    "Score": "",
    "Away": "Leicester City",
    "AwayCode": "LEI"
  },
  {
    "Wk": 38,
    "Date": "2025-05-25",
    "Time": "16:00",
    "Home": "Newcastle Utd",
    "HomeCode": "NEW",
    "Score": "",
    "Away": "Everton",
    "AwayCode": "EVE"
  },
  {
    "Wk": 38,
    "Date": "2025-05-25",
    "Time": "16:00",
    "Home": "Fulham",
    "HomeCode": "FUL",
    "Score": "",
    "Away": "Manchester City",
    "AwayCode": "MCI"
  },
  {
    "Wk": 38,
    "Date": "2025-05-25",
    "Time": "16:00",
    "Home": "Nott'ham Forest",
    "HomeCode": "NFO",
    "Score": "",
    "Away": "Chelsea",
    "AwayCode": "CHE"
  },
  {
    "Wk": 38,
    "Date": "2025-05-25",
    "Time": "16:00",
    "Home": "Manchester Utd",
    "HomeCode": "MUN",
    "Score": "",
    "Away": "Aston Villa",
    "AwayCode": "AVL"
  },
  {
    "Wk": 38,
    "Date": "2025-05-25",
    "Time": "16:00",
    "Home": "Wolves",
    "HomeCode": "WOL",
    "Score": "",
    "Away": "Brentford",
    "AwayCode": "BRE"
  },
  {
    "Wk": 38,
    "Date": "2025-05-25",
    "Time": "16:00",
    "Home": "Tottenham",
    "HomeCode": "TOT",
    "Score": "",
    "Away": "Brighton",
    "AwayCode": "BHA"
  }
]
